pypear/__init__.py
pypear/install.py
pypear/vimrc_template
pypear/vim/plugins.zip
pypear-0.0.20.dist-info/LICENSE
pypear-0.0.20.dist-info/METADATA
pypear-0.0.20.dist-info/WHEEL
pypear-0.0.20.dist-info/entry_points.txt
pypear-0.0.20.dist-info/top_level.txt
pypear-0.0.20.dist-info/RECORD
