Metadata-Version: 2.1
Name: pypear
Version: 0.0.20
Summary: Terminal based python development
Home-page: https://github.com/brianmcconnel/pypear
Author: Brian McConnel
Author-email: brianmcconnel@gmail.com
License: MIT
Keywords: python,tmux,vim,pypear
Classifier: License :: OSI Approved :: MIT License
Classifier: Programming Language :: Python :: 3
Classifier: Programming Language :: Python :: 3 :: Only
Classifier: Programming Language :: Python :: 3.6
Classifier: Programming Language :: Python :: 3.7
Classifier: Programming Language :: Python :: 3.8
Classifier: Programming Language :: Python :: Implementation :: CPython
Classifier: Programming Language :: Python :: Implementation :: PyPy
Requires-Python: >=3.6.1
License-File: LICENSE
Requires-Dist: autopep8
Requires-Dist: flake8
Requires-Dist: pytest
Requires-Dist: pre-commit
Requires-Dist: pre-commit-hooks
